.bumpversion.cfg
.cookiecutterrc
.coveragerc
.editorconfig
.gitignore
AUTHORS.rst
CHANGELOG.rst
CONTRIBUTING.rst
LICENSE
MANIFEST.in
Makefile
README.rst
requirements.txt
setup.cfg
setup.py
ci/bootstrap.py
docs/authors.rst
docs/changelog.rst
docs/conf.py
docs/contributing.rst
docs/index.rst
docs/installation.rst
docs/readme.rst
docs/requirements.txt
docs/spelling_wordlist.txt
docs/usage.rst
docs/reference/index.rst
docs/reference/mqttcat.rst
src/mqttcat/__init__.py
src/mqttcat/__main__.py
src/mqttcat/cli.py
src/mqttcat/emittarget.py
src/mqttcat.egg-info/PKG-INFO
src/mqttcat.egg-info/SOURCES.txt
src/mqttcat.egg-info/dependency_links.txt
src/mqttcat.egg-info/entry_points.txt
src/mqttcat.egg-info/not-zip-safe
src/mqttcat.egg-info/requires.txt
src/mqttcat.egg-info/top_level.txt
tests/test_mqttcat.py