Metadata-Version: 1.1
Name: mqttcat
Version: 0.1.2
Summary: Netcat for MQTT
Home-page: https://github.com/martinvirtel/python-mqttcat
Author: Martin Virtel
Author-email: mv@datenfreunde.com
License: BSD 2-Clause License
Keywords: mqtt
Platform: UNKNOWN
Classifier: Development Status :: 3 - Alpha
Classifier: Intended Audience :: Developers
Classifier: License :: OSI Approved :: BSD License
Classifier: Operating System :: Unix
Classifier: Programming Language :: Python :: 3.6
Classifier: Topic :: Utilities
